LICENSE
README.md
setup.py
string_grab/__init__.py
string_grab/string_grab.py
string_grab.egg-info/PKG-INFO
string_grab.egg-info/SOURCES.txt
string_grab.egg-info/dependency_links.txt
string_grab.egg-info/top_level.txt