Metadata-Version: 2.1
Name: string-grab
Version: 1.3.0
Summary: Extract one or multiple substrings between two start and end strings.
Home-page: https://github.com/Julynx/string_grab
Author: Julio Cabria
Author-email: juliocabria@tutanota.com
Maintainer: Julio Cabria
Maintainer-email: juliocabria@tutanota.com
License: GPLv2
License-File: LICENSE
